dbeat/__init__.py
dbeat/database.py
dbeat/models.py
dbeat/schedulers.py
dbeat/tzcrontab.py
dbeat/utils.py
dbeat-1.0.4.dist-info/METADATA
dbeat-1.0.4.dist-info/WHEEL
dbeat-1.0.4.dist-info/entry_points.txt
dbeat-1.0.4.dist-info/top_level.txt
dbeat-1.0.4.dist-info/RECORD
