Metadata-Version: 2.1
Name: dbeat
Version: 1.0.4
Summary: Database-backed Periodic Tasks.
Home-page: https://github.com/aohan237/dbeat
Author: aohan237
Author-email: aohan237@gmail.com
License: BSD
Keywords: peewee celery beat periodic task database
Platform: any
Classifier: Development Status :: 5 - Production/Stable
Classifier: License :: OSI Approved :: BSD License
Classifier: Programming Language :: Python
Classifier: Programming Language :: Python :: 2
Classifier: Programming Language :: Python :: 2.7
Classifier: Programming Language :: Python :: 3
Classifier: Programming Language :: Python :: 3.4
Classifier: Programming Language :: Python :: 3.5
Classifier: Programming Language :: Python :: 3.6
Classifier: Programming Language :: Python :: 3.7
Classifier: Programming Language :: Python :: Implementation :: CPython
Classifier: Programming Language :: Python :: Implementation :: PyPy
Classifier: Operating System :: OS Independent
Classifier: Topic :: Communications
Classifier: Topic :: System :: Distributed Computing
Classifier: Topic :: Software Development :: Libraries :: Python Modules
Requires-Dist: celery (<5.0,>=4.0)
Requires-Dist: peewee (>=3.7)
